primeight/__init__.py
primeight/base.py
primeight/column.py
primeight/exceptions.py
primeight/generators.py
primeight/keyspace.py
primeight/manager.py
primeight/table.py
primeight/utils.py
primeight/parser/__init__.py
primeight/parser/parser.py
primeight/parser/yaml_parser.py
primeight-0.1.6.dist-info/METADATA
primeight-0.1.6.dist-info/WHEEL
primeight-0.1.6.dist-info/top_level.txt
primeight-0.1.6.dist-info/RECORD
